pulldistros.py
pulldistros-0.2.dist-info/DESCRIPTION.rst
pulldistros-0.2.dist-info/METADATA
pulldistros-0.2.dist-info/RECORD
pulldistros-0.2.dist-info/WHEEL
pulldistros-0.2.dist-info/metadata.json
pulldistros-0.2.dist-info/top_level.txt
