Metadata-Version: 2.0
Name: pulldistros
Version: 0.2
Summary: Scrape distrowatch.com
Home-page: https://github.com/ofosos/pulldistros
Author: Mark Meyer
Author-email: mark@ofosos.org
License: UNKNOWN
Keywords: scape web distrowatch
Platform: UNKNOWN
Classifier: Development Status :: 3 - Alpha
Classifier: Intended Audience :: Developers
Classifier: License :: OSI Approved :: GNU Affero General Public License v3 or later (AGPLv3+)
Classifier: Programming Language :: Python :: 2
Classifier: Programming Language :: Python :: 2.7
Classifier: Programming Language :: Python :: 3
Classifier: Programming Language :: Python :: 3.4
Classifier: Programming Language :: Python :: 3.5
Classifier: Programming Language :: Python :: 3.6
Requires-Dist: bs4
Requires-Dist: requests
Requires-Dist: requests-cache
Requires-Dist: html5lib
